{
  "globalLineCoverage": "98.32%",
  "totalFilesWithGaps": 34,
  "gaps": [
    {
      "class": "sgc.subprocesso.service.workflow.SubprocessoMapaWorkflowService",
      "coverage": "96.90%",
      "missed": [
        88,
        89,
        112,
        113,
        249,
        274,
        296
      ],
      "partial": [
        "87(1/2)",
        "111(1/2)",
        "145(1/2)",
        "248(1/2)",
        "273(1/2)",
        "295(1/2)",
        "323(1/2)",
        "329(1/2)"
      ],
      "score": 11
    },
    {
      "class": "sgc.subprocesso.model.SituacaoSubprocesso",
      "coverage": "100.00%",
      "missed": [],
      "partial": [
        "42(1/4)",
        "50(2/12)",
        "59(1/4)",
        "63(1/6)",
        "68(1/4)",
        "72(1/6)",
        "77(1/4)",
        "81(1/4)",
        "88(1/2)",
        "91(1/6)",
        "96(1/6)",
        "101(1/4)",
        "105(1/6)",
        "110(1/4)",
        "114(1/4)",
        "119(1/2)",
        "122(1/2)"
      ],
      "score": 8.5
    },
    {
      "class": "sgc.mapa.MapaController",
      "coverage": "82.14%",
      "missed": [
        58,
        76,
        82,
        100,
        105
      ],
      "partial": [
        "57(1/2)",
        "75(1/2)",
        "81(1/2)",
        "99(1/2)",
        "104(1/2)"
      ],
      "score": 7.5
    },
    {
      "class": "sgc.mapa.service.MapaManutencaoService",
      "coverage": "95.63%",
      "missed": [
        327,
        332,
        337,
        346,
        351,
        355,
        356
      ],
      "partial": [],
      "score": 7
    },
    {
      "class": "sgc.processo.listener.EventoProcessoListener",
      "coverage": "96.21%",
      "missed": [
        245,
        253,
        294,
        295,
        296
      ],
      "partial": [
        "213(2/4)",
        "244(1/2)",
        "250(1/3)"
      ],
      "score": 6.5
    },
    {
      "class": "sgc.mapa.service.ImpactoMapaService",
      "coverage": "95.74%",
      "missed": [
        87,
        215,
        308,
        309,
        310,
        311
      ],
      "partial": [],
      "score": 6
    },
    {
      "class": "sgc.processo.service.ProcessoFacade",
      "coverage": "95.74%",
      "missed": [
        71,
        81,
        151,
        184
      ],
      "partial": [
        "70(1/2)",
        "80(1/2)",
        "169(1/2)",
        "246(1/2)"
      ],
      "score": 6
    },
    {
      "class": "sgc.seguranca.login.GerenciadorJwt",
      "coverage": "92.06%",
      "missed": [
        123,
        124,
        129,
        130,
        131
      ],
      "partial": [
        "122(1/2)"
      ],
      "score": 5.5
    },
    {
      "class": "sgc.subprocesso.service.SubprocessoFacade",
      "coverage": "97.22%",
      "missed": [
        86,
        407,
        408
      ],
      "partial": [
        "242(1/2)",
        "251(1/2)",
        "316(1/2)",
        "325(1/2)",
        "334(1/2)"
      ],
      "score": 5.5
    },
    {
      "class": "sgc.e2e.E2eController",
      "coverage": "95.88%",
      "missed": [
        87,
        88,
        89,
        244
      ],
      "partial": [
        "210(1/4)",
        "234(1/2)"
      ],
      "score": 5
    },
    {
      "class": "sgc.subprocesso.service.crud.SubprocessoCrudService",
      "coverage": "95.08%",
      "missed": [
        91,
        104,
        154
      ],
      "partial": [
        "90(1/2)",
        "103(1/2)",
        "153(1/2)"
      ],
      "score": 4.5
    },
    {
      "class": "sgc.mapa.service.MapaSalvamentoService",
      "coverage": "97.06%",
      "missed": [
        74,
        227,
        228
      ],
      "partial": [
        "73(1/2)",
        "163(1/2)",
        "226(1/2)"
      ],
      "score": 4.5
    },
    {
      "class": "sgc.processo.ProcessoController",
      "coverage": "93.18%",
      "missed": [
        184,
        286,
        287
      ],
      "partial": [
        "183(1/2)"
      ],
      "score": 3.5
    },
    {
      "class": "sgc.seguranca.login.LoginController",
      "coverage": "97.83%",
      "missed": [
        153
      ],
      "partial": [
        "60(1/2)",
        "122(1/2)",
        "123(1/2)",
        "150(1/2)"
      ],
      "score": 3
    },
    {
      "class": "sgc.seguranca.login.LoginFacade",
      "coverage": "95.45%",
      "missed": [
        74,
        126
      ],
      "partial": [
        "125(1/2)"
      ],
      "score": 2.5
    },
    {
      "class": "sgc.seguranca.acesso.AtividadeAccessPolicy",
      "coverage": "93.10%",
      "missed": [
        66,
        67
      ],
      "partial": [
        "65(1/2)"
      ],
      "score": 2.5
    },
    {
      "class": "sgc.organizacao.service.UsuarioConsultaService",
      "coverage": "86.67%",
      "missed": [
        57,
        61
      ],
      "partial": [],
      "score": 2
    },
    {
      "class": "sgc.processo.service.ProcessoFinalizador",
      "coverage": "92.86%",
      "missed": [
        89,
        93
      ],
      "partial": [],
      "score": 2
    },
    {
      "class": "sgc.subprocesso.service.SubprocessoAjusteMapaService",
      "coverage": "98.51%",
      "missed": [
        98
      ],
      "partial": [
        "97(1/2)",
        "163(1/2)"
      ],
      "score": 2
    },
    {
      "class": "sgc.subprocesso.service.query.ProcessoSubprocessoQueryService",
      "coverage": "88.24%",
      "missed": [
        84,
        107
      ],
      "partial": [],
      "score": 2
    },
    {
      "class": "sgc.organizacao.service.UnidadeHierarquiaService",
      "coverage": "98.82%",
      "missed": [
        231
      ],
      "partial": [
        "230(1/2)"
      ],
      "score": 1.5
    },
    {
      "class": "sgc.subprocesso.SubprocessoCadastroController",
      "coverage": "98.41%",
      "missed": [
        320
      ],
      "partial": [
        "319(1/2)"
      ],
      "score": 1.5
    },
    {
      "class": "sgc.organizacao.UsuarioFacade",
      "coverage": "100.00%",
      "missed": [],
      "partial": [
        "75(1/6)",
        "200(1/2)",
        "215(1/2)"
      ],
      "score": 1.5
    },
    {
      "class": "sgc.mapa.service.MapaFacade",
      "coverage": "96.88%",
      "missed": [
        87
      ],
      "partial": [
        "86(1/2)"
      ],
      "score": 1.5
    },
    {
      "class": "sgc.subprocesso.service.workflow.SubprocessoAdminWorkflowService",
      "coverage": "96.55%",
      "missed": [
        42
      ],
      "partial": [
        "38(1/2)"
      ],
      "score": 1.5
    },
    {
      "class": "sgc.subprocesso.service.SubprocessoAtividadeService",
      "coverage": "98.04%",
      "missed": [
        93
      ],
      "partial": [
        "89(1/3)"
      ],
      "score": 1.5
    },
    {
      "class": "sgc.seguranca.acesso.AbstractAccessPolicy",
      "coverage": "98.11%",
      "missed": [
        123
      ],
      "partial": [
        "122(1/5)"
      ],
      "score": 1.5
    },
    {
      "class": "sgc.organizacao.service.UnidadeMapaService",
      "coverage": "85.71%",
      "missed": [
        47
      ],
      "partial": [],
      "score": 1
    },
    {
      "class": "sgc.organizacao.service.UsuarioPerfilService",
      "coverage": "88.89%",
      "missed": [
        40
      ],
      "partial": [],
      "score": 1
    },
    {
      "class": "sgc.mapa.service.CopiaMapaService",
      "coverage": "100.00%",
      "missed": [],
      "partial": [
        "115(1/2)",
        "139(1/2)"
      ],
      "score": 1
    },
    {
      "class": "sgc.configuracao.ConfiguracaoService",
      "coverage": "90.91%",
      "missed": [
        44
      ],
      "partial": [],
      "score": 1
    },
    {
      "class": "sgc.processo.service.ProcessoConsultaService",
      "coverage": "97.50%",
      "missed": [
        65
      ],
      "partial": [],
      "score": 1
    },
    {
      "class": "sgc.organizacao.service.ValidadorDadosOrgService",
      "coverage": "100.00%",
      "missed": [],
      "partial": [
        "92(1/4)"
      ],
      "score": 0.5
    },
    {
      "class": "sgc.organizacao.UnidadeController",
      "coverage": "100.00%",
      "missed": [],
      "partial": [
        "88(2/4)"
      ],
      "score": 0.5
    }
  ]
}